gptel/__init__.py
gptel/base.py
gptel/bot.py
gptel/services.py
gptel/telegram_client.py
gptel/utils.py
gptel-0.3.0.dist-info/METADATA
gptel-0.3.0.dist-info/WHEEL
gptel-0.3.0.dist-info/RECORD
