Metadata-Version: 2.1
Name: gptel
Version: 0.3.0
Summary: Framework to build Telegram bots
Author: Cristóbal Carnero Liñán
Author-email: ccarnerolinan@gmail.com
Requires-Python: >=3.9,<4.0
Classifier: Programming Language :: Python :: 3
Classifier: Programming Language :: Python :: 3.9
Classifier: Programming Language :: Python :: 3.10
Classifier: Programming Language :: Python :: 3.11
Classifier: Programming Language :: Python :: 3.12
Requires-Dist: openai (>=1.12.0,<2.0.0)
Requires-Dist: python-telegram-bot (>=20.8,<21.0)
